McGyverLabyrinth/__init__.py
McGyverLabyrinth/class_game.py
McGyverLabyrinth/game.py
McGyverLabyrinth/level.csv
McGyverLabyrinth/pictures/gameover.png
McGyverLabyrinth/pictures/guardian.png
McGyverLabyrinth/pictures/macgyver.png
McGyverLabyrinth/pictures/stuff_1.png
McGyverLabyrinth/pictures/stuff_2.png
McGyverLabyrinth/pictures/stuff_3.png
McGyverLabyrinth/pictures/stuff_4.png
McGyverLabyrinth/pictures/stuff_5.png
McGyverLabyrinth/pictures/stuff_6.png
McGyverLabyrinth/pictures/stuff_7.png
McGyverLabyrinth/pictures/wall.png
McGyverLabyrinth/pictures/win.png
McGyverLabyrinth-0.0.5.dist-info/DESCRIPTION.rst
McGyverLabyrinth-0.0.5.dist-info/METADATA
McGyverLabyrinth-0.0.5.dist-info/RECORD
McGyverLabyrinth-0.0.5.dist-info/WHEEL
McGyverLabyrinth-0.0.5.dist-info/metadata.json
McGyverLabyrinth-0.0.5.dist-info/top_level.txt
