Metadata-Version: 2.0
Name: McGyverLabyrinth
Version: 0.0.5
Summary: UNKNOWN
Home-page: https://github.com/NanroYahel/P3_Labyrinthe
Author: Ronan LE HAY
Author-email: ronanlehay@gmail.com
License: UNKNOWN
Platform: UNKNOWN
Requires-Dist: numpy (==1.13.1)
Requires-Dist: pandas (==0.20.3)
Requires-Dist: pygame (==1.9.3)
Requires-Dist: python-dateutil (==2.6.1)
Requires-Dist: pytz (==2017.2)
Requires-Dist: six (==1.10.0)
